Metadata-Version: 2.1
Name: bigjpg
Version: 1.2.0
Summary: Wrappper for https://bigjpg.com/
Author: Marcuth
Author-email: example@gmail.com
License: MIT License
Keywords: bigjpg wrapper api
Requires-Dist: requests
Requires-Dist: pydantic
Requires-Dist: rich
